Metadata-Version: 2.1
Name: bgapi2
Version: 0.8
Summary: Interface library for BlueGiga BLE112 and BLE113 modules
Home-page: https://github.com/mjbrown/bgapi
Author: Michael Brown
Author-email: mjbrown.droid@gmail.com
Classifier: Development Status :: 3 - Alpha
Classifier: Intended Audience :: Developers
Classifier: License :: OSI Approved :: Mozilla Public License 2.0 (MPL 2.0)
Classifier: Programming Language :: Python :: 2.7
Classifier: Programming Language :: Python :: 3
Classifier: Programming Language :: Python :: 3.5
Classifier: Topic :: Software Development :: Libraries
Classifier: Operating System :: OS Independent
